LICENSE
MANIFEST.in
koremutake.py
setup.py
koremutake.egg-info/PKG-INFO
koremutake.egg-info/SOURCES.txt
koremutake.egg-info/dependency_links.txt
koremutake.egg-info/top_level.txt