Metadata-Version: 1.0
Name: koremutake
Version: 1.1.0
Summary: Convert to and from Koremutake Memorable Random Strings
Home-page: http://github.com/pschork/koremutake
Author: Patrick Schork
Author-email: patrick@schork.com
License: BSD
Keywords: koremutake kormutake koremutate kormutate shorl mers tinyurl
Platform: UNKNOWN
